balderhub/selenium/__init__.py
balderhub/selenium/_version.py
balderhub/selenium/lib/__init__.py
balderhub/selenium/lib/scenario_features/__init__.py
balderhub/selenium/lib/scenario_features/selenium_feature.py
balderhub/selenium/lib/scenario_features/selenium_proxy.py
balderhub/selenium/lib/setup_features/__init__.py
balderhub/selenium/lib/setup_features/selenium_chrome_webdriver_feature.py
balderhub/selenium/lib/setup_features/selenium_edge_webdriver_feature.py
balderhub/selenium/lib/setup_features/selenium_firefox_webdriver_feature.py
balderhub/selenium/lib/setup_features/selenium_ie_webdriver_feature.py
balderhub/selenium/lib/setup_features/selenium_remote_webdriver_feature.py
balderhub/selenium/lib/setup_features/selenium_safari_webdriver_feature.py
balderhub/selenium/lib/utils/__init__.py
balderhub/selenium/lib/utils/selector.py
balderhub/selenium/lib/utils/drivers/__init__.py
balderhub/selenium/lib/utils/drivers/base_selenium_driver.py
balderhub/selenium/lib/utils/drivers/selenium_chrome_driver.py
balderhub/selenium/lib/utils/drivers/selenium_edge_driver.py
balderhub/selenium/lib/utils/drivers/selenium_firefox_driver.py
balderhub/selenium/lib/utils/drivers/selenium_ie_driver.py
balderhub/selenium/lib/utils/drivers/selenium_remote_driver.py
balderhub/selenium/lib/utils/drivers/selenium_safari_driver.py
balderhub/selenium/lib/utils/web_element_bridges/__init__.py
balderhub/selenium/lib/utils/web_element_bridges/selenium_fully_reidentifiable_element_bridge.py
balderhub/selenium/lib/utils/web_element_bridges/selenium_not_reidentifiable_element_bridge.py
balderhub/selenium/lib/utils/web_element_bridges/selenium_partly_reidentifiable_element_bridge.py
balderhub/selenium/lib/utils/web_element_bridges/selenium_web_element_bridge.py
balderhub_selenium-0.0.1b0.dist-info/licenses/LICENSE
balderhub_selenium-0.0.1b0.dist-info/METADATA
balderhub_selenium-0.0.1b0.dist-info/WHEEL
balderhub_selenium-0.0.1b0.dist-info/top_level.txt
balderhub_selenium-0.0.1b0.dist-info/RECORD
